solveJsonEquation/__init__.py
solveJsonEquation/expression.py
solveJsonEquation/operatorUtils.py
solveJsonEquation/solver.py
equation_solver_abhhii-0.0.1.dist-info/LICENSE
equation_solver_abhhii-0.0.1.dist-info/METADATA
equation_solver_abhhii-0.0.1.dist-info/WHEEL
equation_solver_abhhii-0.0.1.dist-info/top_level.txt
equation_solver_abhhii-0.0.1.dist-info/RECORD
