Metadata-Version: 2.1
Name: equation-solver-abhhii
Version: 0.0.1
Summary: This package allows us to solve linear equations encoded in json form
Home-page: https://github.com/abhhii/equationSolver
Author: Abhishek Singhal
Author-email: abhhii.cse@gmail.com
License: UNKNOWN
Platform: UNKNOWN
Classifier: Programming Language :: Python :: 3
Classifier: License :: OSI Approved :: MIT License
Classifier: Operating System :: OS Independent
Requires-Python: >=3.6
